blue_cemetery/README.py
blue_cemetery/__init__.py
blue_cemetery/__main__.py
blue_cemetery/functions.py
blue_cemetery/host.py
blue_cemetery/logger.py
blue_cemetery/urls.py
blue_cemetery/.abcli/abcli.sh
blue_cemetery/.abcli/actions.sh
blue_cemetery/.abcli/alias.sh
blue_cemetery/.abcli/blue_cemetery.sh
blue_cemetery/.abcli/browse.sh
blue_cemetery/.abcli/cemetery/DALLE.sh
blue_cemetery/.abcli/cemetery/VisuaLyze.sh
blue_cemetery/.abcli/cemetery/blue_sam.sh
blue_cemetery/.abcli/cemetery/generate_function.sh
blue_cemetery/.abcli/cemetery/gpt.sh
blue_cemetery/.abcli/cemetery/microsoft_building_damage_assessment.sh
blue_cemetery/.abcli/cemetery/blue_sam/install.sh
blue_cemetery/.abcli/cemetery/inference/cloudwatch.sh
blue_cemetery/.abcli/cemetery/inference/inference.sh
blue_cemetery/.abcli/cemetery/microsoft_building_damage_assessment/ingest.sh
blue_cemetery/.abcli/cemetery/microsoft_building_damage_assessment/install.sh
blue_cemetery/.abcli/cemetery/microsoft_building_damage_assessment/label.sh
blue_cemetery/.abcli/cemetery/microsoft_building_damage_assessment/tensorboard.sh
blue_cemetery/.abcli/cemetery/microsoft_building_damage_assessment/train.sh
blue_cemetery/.abcli/cemetery/microsoft_building_damage_assessment/ingest/list.sh
blue_cemetery/.abcli/cemetery/sagesemseg/cache_dataset.sh
blue_cemetery/.abcli/cemetery/sagesemseg/consts.sh
blue_cemetery/.abcli/cemetery/sagesemseg/train.sh
blue_cemetery/.abcli/cemetery/sagesemseg/upload_dataset.sh
blue_cemetery/.abcli/tests/README.sh
blue_cemetery/.abcli/tests/help.sh
blue_cemetery/.abcli/tests/version.sh
blue_cemetery/.abcli/tests/cemetery/microsoft_building_damage_assessment_ingest.sh
blue_cemetery/.abcli/tests/cemetery/microsoft_building_damage_assessment_ingest_list.sh
blue_cemetery/.abcli/tests/cemetery/microsoft_building_damage_assessment_label.sh
blue_cemetery/.abcli/tests/cemetery/microsoft_building_damage_assessment_train.sh
blue_cemetery/.abcli/tests/cemetery/sagesemseg_train.sh
blue_cemetery/help/__init__.py
blue_cemetery-3.242.1.dist-info/LICENSE
blue_cemetery-3.242.1.dist-info/METADATA
blue_cemetery-3.242.1.dist-info/WHEEL
blue_cemetery-3.242.1.dist-info/top_level.txt
blue_cemetery-3.242.1.dist-info/RECORD
